proxy_fn/__init__.py
proxy_fn/proxy_fn.py
proxy_fn-3.1.3.dist-info/LICENSE
proxy_fn-3.1.3.dist-info/METADATA
proxy_fn-3.1.3.dist-info/WHEEL
proxy_fn-3.1.3.dist-info/top_level.txt
proxy_fn-3.1.3.dist-info/RECORD
