Metadata-Version: 2.1
Name: proxy-fn
Version: 3.1.3
Summary: Python functions for proxy.
Home-page: https://github.com/VisionNetworkProject/python-proxy-fn
Author: Vision Network
Author-email: michael@vision.network
License: UNKNOWN
Keywords: Functions,Proxy
Platform: UNKNOWN
Classifier: Programming Language :: Python :: 3
Classifier: License :: OSI Approved :: MIT License
Classifier: Operating System :: OS Independent
Requires-Dist: cli-print
Requires-Dist: qwert
Requires-Dist: ip-query
